<?xml version="1.0" encoding="UTF-8" standalone="yes"?>
<duties>
    <period yearsMin="0" yearsMax="3">
        <rates volumeMin="null" volumeMax="null" priceMin="0" priceMax="8500" fromCost="0.54" bid="2.5"/>
        <rates volumeMin="null" volumeMax="null" priceMin="8501" priceMax="16700" fromCost="0.48" bid="3.5"/>
        <rates volumeMin="null" volumeMax="null" priceMin="16700" priceMax="42300" fromCost="0.48" bid="5.5"/>
        <rates volumeMin="null" volumeMax="null" priceMin="42300" priceMax="84500" fromCost="0.48" bid="7.5"/>
        <rates volumeMin="null" volumeMax="null" priceMin="84500" priceMax="169000" fromCost="0.48" bid="15"/>
        <rates volumeMin="null" volumeMax="null" priceMin="169000" priceMax="null" fromCost="0.48" bid="20"/>
    </period>
    <period yearsMin="3" yearsMax="5">
        <rates volumeMin="0" volumeMax="1000" priceMin="null" priceMax="null" fromCost="null" bid="1.5" />
        <rates volumeMin="1001" volumeMax="1500" priceMin="null" priceMax="null" fromCost="null" bid="1.7" />
        <rates volumeMin="1501" volumeMax="1800" priceMin="null" priceMax="null" fromCost="null" bid="2.5" />
        <rates volumeMin="1801" volumeMax="2300" priceMin="null" priceMax="null" fromCost="null" bid="2.7" />
        <rates volumeMin="2300" volumeMax="3000" priceMin="null" priceMax="null" fromCost="null" bid="3" />
        <rates volumeMin="3000" volumeMax="null" priceMin="null" priceMax="null" fromCost="null" bid="3.6" />
    </period>
    <period yearsMin="5" yearsMax="null">
        <rates volumeMin="0" volumeMax="1000" priceMin="null" priceMax="null" fromCost="null" bid="3" />
        <rates volumeMin="1001" volumeMax="1500" priceMin="null" priceMax="null" fromCost="null" bid="3.2" />
        <rates volumeMin="1501" volumeMax="1800" priceMin="null" priceMax="null" fromCost="null" bid="3.5" />
        <rates volumeMin="1801" volumeMax="2300" priceMin="null" priceMax="null" fromCost="null" bid="4.8" />
        <rates volumeMin="2300" volumeMax="3000" priceMin="null" priceMax="null" fromCost="null" bid="5" />
        <rates volumeMin="3000" volumeMax="null" priceMin="null" priceMax="null" fromCost="null" bid="5.7" />
    </period>
</duties>
